Metadata-Version: 1.0
Name: mlnd-probdist
Version: 0.0.1
Summary: Gaussian and Binomial distributions
Home-page: UNKNOWN
Author: Chandrakanth Nethi
Author-email: chandrakanth.nethi@gmail.com
License: UNKNOWN
Platform: UNKNOWN
